examples/rosenbrock.py
examples/networks/compare.py
examples/networks/datasets.py
examples/networks/manager.py
examples/networks/models.py
mlx_optimizers/__init__.py
mlx_optimizers/adopt.py
mlx_optimizers/common.py
mlx_optimizers/diffgrad.py
mlx_optimizers/kron.py
mlx_optimizers/lamb.py
mlx_optimizers/madgrad.py
mlx_optimizers/mars.py
mlx_optimizers/muon.py
mlx_optimizers/py.typed
mlx_optimizers/qhadam.py
mlx_optimizers/shampoo.py
mlx_optimizers/version.py
mlx_optimizers-0.4.1.dist-info/LICENSE
mlx_optimizers-0.4.1.dist-info/METADATA
mlx_optimizers-0.4.1.dist-info/WHEEL
mlx_optimizers-0.4.1.dist-info/top_level.txt
mlx_optimizers-0.4.1.dist-info/RECORD
