Metadata-Version: 2.1
Name: mlx-optimizers
Version: 0.4.1
Author-email: Jason Stock <jason12stock@gmail.com>
License:                                  Apache License
Project-URL: Homepage, https://github.com/stockeh/mlx-optimizers
Project-URL: Repository, https://github.com/stockeh/mlx-optimizers
Project-URL: Changelog, https://github.com/stockeh/mlx-optimizers/blob/main/CHANGELOG.md
Classifier: Intended Audience :: Science/Research
Classifier: Development Status :: 3 - Alpha
Classifier: License :: OSI Approved :: Apache Software License
Classifier: Programming Language :: Python :: 3
Classifier: Topic :: Scientific/Engineering :: Artificial Intelligence
Requires-Python: >=3.10
License-File: LICENSE
Requires-Dist: mlx>=0.18.0
Provides-Extra: dev
Requires-Dist: ruff; extra == "dev"
Requires-Dist: mypy<1.14,>=1.13.0; extra == "dev"
Requires-Dist: black<25.0,>=24.10.0; extra == "dev"
Requires-Dist: isort<5.14,>=5.13.2; extra == "dev"
Requires-Dist: pytest; extra == "dev"
Requires-Dist: pytest-sphinx; extra == "dev"
Requires-Dist: pytest-cov; extra == "dev"
Requires-Dist: twine>=5.1.1; extra == "dev"
Requires-Dist: build; extra == "dev"
Requires-Dist: setuptools; extra == "dev"
Requires-Dist: wheel; extra == "dev"
Requires-Dist: Sphinx<8.2.0,>=8.1.3; extra == "dev"
Requires-Dist: furo==2024.8.6; extra == "dev"
Requires-Dist: myst-parser<4.1,>=4.0.0; extra == "dev"
Requires-Dist: sphinx-copybutton==0.5.2; extra == "dev"
Requires-Dist: sphinx-autobuild==2024.10.3; extra == "dev"
Requires-Dist: sphinx-autodoc-typehints==2.5.0; extra == "dev"
Requires-Dist: packaging; extra == "dev"
Requires-Dist: sphinx-book-theme; extra == "dev"
